{
  "국토교통부_등록번호용 지역코드_20221231": {
    "1100": {
      "행정구역": "서울특별시",
      "기관_명": "서울특별시"
    },
    "1111": {
      "행정구역": "서울특별시 종로구",
      "기관_명": "종로구"
    },
    "1112": {
      "행정구역": "서울특별시 중구",
      "기관_명": "중구"
    },
    "1113": {
      "행정구역": "서울특별시 용산구",
      "기관_명": "용산구"
    },
    "1114": {
      "행정구역": "서울특별시 성동구",
      "기관_명": "성동구"
    },
    "1115": {
      "행정구역": "서울특별시 동대문구",
      "기관_명": "동대문구"
    },
    "1116": {
      "행정구역": "서울특별시 성북구",
      "기관_명": "성북구"
    },
    "1117": {
      "행정구역": "서울특별시 도봉구",
      "기관_명": "도봉구"
    },
    "1118": {
      "행정구역": "서울특별시 은평구",
      "기관_명": "은평구"
    },
    "1119": {
      "행정구역": "서울특별시 서대문구",
      "기관_명": "서대문구"
    },
    "1120": {
      "행정구역": "서울특별시 마포구",
      "기관_명": "마포구"
    },
    "1121": {
      "행정구역": "서울특별시 강서구",
      "기관_명": "강서구"
    },
    "1122": {
      "행정구역": "서울특별시 구로구",
      "기관_명": "구로구"
    },
    "1123": {
      "행정구역": "서울특별시 영등포구",
      "기관_명": "영등포구"
    },
    "1124": {
      "행정구역": "서울특별시 동작구",
      "기관_명": "동작구"
    },
    "1125": {
      "행정구역": "서울특별시 관악구",
      "기관_명": "관악구"
    },
    "1126": {
      "행정구역": "서울특별시 강남구",
      "기관_명": "강남구"
    },
    "1127": {
      "행정구역": "서울특별시 강동구",
      "기관_명": "강동구"
    },
    "1128": {
      "행정구역": "서울특별시 중랑구",
      "기관_명": "중랑구"
    },
    "1129": {
      "행정구역": "서울특별시 노원구",
      "기관_명": "노원구"
    },
    "1130": {
      "행정구역": "서울특별시 양천구",
      "기관_명": "양천구"
    },
    "1131": {
      "행정구역": "서울특별시 서초구",
      "기관_명": "서초구"
    },
    "1132": {
      "행정구역": "서울특별시 송파구",
      "기관_명": "송파구"
    },
    "1133": {
      "행정구역": "서울특별시 광진구",
      "기관_명": "광진구"
    },
    "1134": {
      "행정구역": "서울특별시 강북구",
      "기관_명": "강북구"
    },
    "1135": {
      "행정구역": "서울특별시 금천구",
      "기관_명": "금천구"
    },
    "2100": {
      "행정구역": "부산광역시",
      "기관_명": "부산광역시"
    },
    "2111": {
      "행정구역": "부산광역시 중구",
      "기관_명": "중 구"
    },
    "2112": {
      "행정구역": "부산광역시 서구",
      "기관_명": "서 구"
    },
    "2113": {
      "행정구역": "부산광역시 동구",
      "기관_명": "동 구"
    },
    "2114": {
      "행정구역": "부산광역시 영도구",
      "기관_명": "영도구"
    },
    "2115": {
      "행정구역": "부산광역시 부산진구",
      "기관_명": "부산진구"
    },
    "2116": {
      "행정구역": "부산광역시 동래구",
      "기관_명": "동래구"
    },
    "2117": {
      "행정구역": "부산광역시 남구",
      "기관_명": "남 구"
    },
    "2118": {
      "행정구역": "부산광역시 북구",
      "기관_명": "북 구"
    },
    "2119": {
      "행정구역": "부산광역시 해운대구",
      "기관_명": "해운대구"
    },
    "2120": {
      "행정구역": "부산광역시 사하구",
      "기관_명": "사하구"
    },
    "2121": {
      "행정구역": "부산광역시 금정구",
      "기관_명": "금정구"
    },
    "2122": {
      "행정구역": "부산광역시 강서구",
      "기관_명": "강서구"
    },
    "2123": {
      "행정구역": "부산광역시 연제구",
      "기관_명": "연제구"
    },
    "2124": {
      "행정구역": "부산광역시 수영구",
      "기관_명": "수영구"
    },
    "2125": {
      "행정구역": "부산광역시 사상구",
      "기관_명": "사상구"
    },
    "2126": {
      "행정구역": "부산광역시 기장군",
      "기관_명": "기장군"
    },
    "2200": {
      "행정구역": "대구광역시",
      "기관_명": "대구광역시"
    },
    "2211": {
      "행정구역": "대구광역시 중구",
      "기관_명": "중 구"
    },
    "2212": {
      "행정구역": "대구광역시 동구",
      "기관_명": "동 구"
    },
    "2213": {
      "행정구역": "대구광역시 서구",
      "기관_명": "서구"
    },
    "2214": {
      "행정구역": "대구광역시 남구",
      "기관_명": "남 구"
    },
    "2215": {
      "행정구역": "대구광역시 북구",
      "기관_명": "북 구"
    },
    "2216": {
      "행정구역": "대구광역시 수성구",
      "기관_명": "수성구"
    },
    "2217": {
      "행정구역": "대구광역시 달서구",
      "기관_명": "달서구"
    },
    "2218": {
      "행정구역": "대구광역시 달성군",
      "기관_명": "달성군"
    },
    "2219": {
      "행정구역": "대구광역시 군위군",
      "기관_명": "군위군"
    },
    "2300": {
      "행정구역": "인천광역시",
      "기관_명": "인천광역시"
    },
    "2311": {
      "행정구역": "인천광역시 중구",
      "기관_명": "중구"
    },
    "2312": {
      "행정구역": "인천광역시 동구",
      "기관_명": "동 구"
    },
    "2315": {
      "행정구역": "인천광역시 남동구",
      "기관_명": "남동구"
    },
    "2316": {
      "행정구역": "인천광역시 서구",
      "기관_명": "서 구"
    },
    "2317": {
      "행정구역": "인천광역시 연수구",
      "기관_명": "연수구"
    },
    "2318": {
      "행정구역": "인천광역시 부평구",
      "기관_명": "부평구"
    },
    "2319": {
      "행정구역": "인천광역시 계양구",
      "기관_명": "계양구"
    },
    "2320": {
      "행정구역": "인천광역시 강화군",
      "기관_명": "강화군"
    },
    "2321": {
      "행정구역": "인천광역시 옹진군",
      "기관_명": "옹진군"
    },
    "2322": {
      "행정구역": "인천광역시 미추홀구",
      "기관_명": "미추홀구"
    },
    "2400": {
      "행정구역": "광주광역시",
      "기관_명": "광주광역시"
    },
    "2411": {
      "행정구역": "광주광역시 동구",
      "기관_명": "동구"
    },
    "2412": {
      "행정구역": "광주광역시 서구",
      "기관_명": "서 구"
    },
    "2413": {
      "행정구역": "광주광역시 북구",
      "기관_명": "북구"
    },
    "2414": {
      "행정구역": "광주광역시 광산구",
      "기관_명": "광산구"
    },
    "2415": {
      "행정구역": "광주광역시 남구",
      "기관_명": "남구"
    },
    "2500": {
      "행정구역": "대전광역시",
      "기관_명": "대전광역시"
    },
    "2511": {
      "행정구역": "대전광역시 동구",
      "기관_명": "동구"
    },
    "2512": {
      "행정구역": "대전광역시 중구",
      "기관_명": "중구"
    },
    "2513": {
      "행정구역": "대전광역시 서구",
      "기관_명": "서구"
    },
    "2514": {
      "행정구역": "대전광역시 유성구",
      "기관_명": "유성구"
    },
    "2515": {
      "행정구역": "대전광역시 대덕구",
      "기관_명": "대덕구"
    },
    "2600": {
      "행정구역": "울산광역시",
      "기관_명": "울산광역시"
    },
    "2611": {
      "행정구역": "울산광역시 중구",
      "기관_명": "중구"
    },
    "2612": {
      "행정구역": "울산광역시 남구",
      "기관_명": "남구"
    },
    "2613": {
      "행정구역": "울산광역시 동구",
      "기관_명": "동구"
    },
    "2614": {
      "행정구역": "울산광역시 북구",
      "기관_명": "북구"
    },
    "2615": {
      "행정구역": "울산광역시 울주군",
      "기관_명": "울주군"
    },
    "2811": {
      "행정구역": "세종특별자치시",
      "기관_명": "세종특별자치시"
    },
    "3100": {
      "행정구역": "경기도",
      "기관_명": "경기도"
    },
    "3103": {
      "행정구역": "경기도 수원시 장안구",
      "기관_명": "수원시장안구"
    },
    "3104": {
      "행정구역": "경기도 수원시 권선구",
      "기관_명": "수원시권선구"
    },
    "3105": {
      "행정구역": "경기도 성남시 수정구",
      "기관_명": "성남시수정구"
    },
    "3106": {
      "행정구역": "경기도 성남시 중원구",
      "기관_명": "성남시중원구"
    },
    "3107": {
      "행정구역": "경기도 성남시 분당구",
      "기관_명": "성남시분당구"
    },
    "3108": {
      "행정구역": "경기도 안양시 만안구",
      "기관_명": "안양시만안구"
    },
    "3109": {
      "행정구역": "경기도 안양시 동안구",
      "기관_명": "안양시동안구"
    },
    "3113": {
      "행정구역": "경기도 의정부시",
      "기관_명": "의정부시"
    },
    "3115": {
      "행정구역": "경기도 부천시",
      "기관_명": "부천시"
    },
    "3116": {
      "행정구역": "경기도 광명시",
      "기관_명": "광명시"
    },
    "3118": {
      "행정구역": "경기도 동두천시",
      "기관_명": "동두천시"
    },
    "3119": {
      "행정구역": "경기도 구리시",
      "기관_명": "구리시"
    },
    "3120": {
      "행정구역": "경기도 평택시",
      "기관_명": "송탄출장소"
    },
    "3121": {
      "행정구역": "경기도 과천시",
      "기관_명": "과천시"
    },
    "3124": {
      "행정구역": "경기도 오산시",
      "기관_명": "오산시"
    },
    "3125": {
      "행정구역": "경기도 시흥시",
      "기관_명": "시흥시"
    },
    "3126": {
      "행정구역": "경기도 군포시",
      "기관_명": "군포시"
    },
    "3127": {
      "행정구역": "경기도 의왕시",
      "기관_명": "의왕시"
    },
    "3128": {
      "행정구역": "경기도 하남시",
      "기관_명": "하남시"
    },
    "3130": {
      "행정구역": "경기도 수원시 팔달구",
      "기관_명": "수원시팔달구"
    },
    "3140": {
      "행정구역": "경기도 연천군",
      "기관_명": "연천군"
    },
    "3142": {
      "행정구역": "경기도 가평군",
      "기관_명": "가평군"
    },
    "3143": {
      "행정구역": "경기도 양평군",
      "기관_명": "양평군"
    },
    "3150": {
      "행정구역": "경기도 남양주시",
      "기관_명": "남양주시"
    },
    "3151": {
      "행정구역": "경기도 고양시 덕양구",
      "기관_명": "고양시덕양구"
    },
    "3154": {
      "행정구역": "경기도 파주시",
      "기관_명": "파주시"
    },
    "3155": {
      "행정구역": "경기도 이천시",
      "기관_명": "이천시"
    },
    "3156": {
      "행정구역": "경기도 안성시",
      "기관_명": "안성시"
    },
    "3157": {
      "행정구역": "경기도 김포시",
      "기관_명": "김포시"
    },
    "3158": {
      "행정구역": "경기도 화성시",
      "기관_명": "동부출장소"
    },
    "3159": {
      "행정구역": "경기도 광주시",
      "기관_명": "광주시"
    },
    "3160": {
      "행정구역": "경기도 양주시",
      "기관_명": "양주시"
    },
    "3161": {
      "행정구역": "경기도 포천시",
      "기관_명": "포천시"
    },
    "3162": {
      "행정구역": "경기도 수원시 영통구",
      "기관_명": "수원시영통구"
    },
    "3163": {
      "행정구역": "경기도 고양시 일산동구",
      "기관_명": "고양시일산동구"
    },
    "3164": {
      "행정구역": "경기도 고양시 일산서구",
      "기관_명": "고양시일산서구"
    },
    "3165": {
      "행정구역": "경기도 용인시 처인구",
      "기관_명": "용인시처인구"
    },
    "3166": {
      "행정구역": "경기도 용인시 기흥구",
      "기관_명": "용인시기흥구"
    },
    "3167": {
      "행정구역": "경기도 용인시 수지구",
      "기관_명": "용인시수지구"
    },
    "3168": {
      "행정구역": "경기도 안산시 상록구",
      "기관_명": "안산시상록구"
    },
    "3169": {
      "행정구역": "경기도 안산시 단원구",
      "기관_명": "안산시단원구"
    },
    "3170": {
      "행정구역": "경기도 여주시",
      "기관_명": "여주시"
    },
    "3200": {
      "행정구역": "강원특별자치도",
      "기관_명": "강원특별자치도"
    },
    "3211": {
      "행정구역": "강원특별자치도 춘천시",
      "기관_명": "춘천시"
    },
    "3212": {
      "행정구역": "강원특별자치도 원주시",
      "기관_명": "원주시"
    },
    "3213": {
      "행정구역": "강원특별자치도 강릉시",
      "기관_명": "강릉시"
    },
    "3214": {
      "행정구역": "강원특별자치도 동해시",
      "기관_명": "동해시"
    },
    "3215": {
      "행정구역": "강원특별자치도 태백시",
      "기관_명": "태백시"
    },
    "3216": {
      "행정구역": "강원특별자치도 속초시",
      "기관_명": "속초시"
    },
    "3217": {
      "행정구역": "강원특별자치도 삼척시",
      "기관_명": "삼척시"
    },
    "3232": {
      "행정구역": "강원특별자치도 홍천군",
      "기관_명": "홍천군"
    },
    "3233": {
      "행정구역": "강원특별자치도 횡성군",
      "기관_명": "횡성군"
    },
    "3235": {
      "행정구역": "강원특별자치도 영월군",
      "기관_명": "영월군"
    },
    "3236": {
      "행정구역": "강원특별자치도 평창군",
      "기관_명": "평창군"
    },
    "3237": {
      "행정구역": "강원특별자치도 정선군",
      "기관_명": "정선군"
    },
    "3238": {
      "행정구역": "강원특별자치도 철원군",
      "기관_명": "철원군"
    },
    "3239": {
      "행정구역": "강원특별자치도 화천군",
      "기관_명": "화천군"
    },
    "3240": {
      "행정구역": "강원특별자치도 양구군",
      "기관_명": "양구군"
    },
    "3241": {
      "행정구역": "강원특별자치도 인제군",
      "기관_명": "인제군"
    },
    "3242": {
      "행정구역": "강원특별자치도 고성군",
      "기관_명": "고성군"
    },
    "3243": {
      "행정구역": "강원특별자치도 양양군",
      "기관_명": "양양군"
    },
    "3300": {
      "행정구역": "충청북도",
      "기관_명": "충청북도"
    },
    "3312": {
      "행정구역": "충청북도 충주시",
      "기관_명": "충주시"
    },
    "3313": {
      "행정구역": "충청북도 제천시",
      "기관_명": "제천시"
    },
    "3314": {
      "행정구역": "충청북도 청주시 상당구",
      "기관_명": "청주시 상당구"
    },
    "3315": {
      "행정구역": "충청북도 청주시 흥덕구",
      "기관_명": "청주시 흥덕구"
    },
    "3316": {
      "행정구역": "충청북도 청주시 서원구",
      "기관_명": "청주시 서원구"
    },
    "3317": {
      "행정구역": "충청북도 청주시 청원구",
      "기관_명": "청주시 청원구"
    },
    "3332": {
      "행정구역": "충청북도 보은군",
      "기관_명": "보은군"
    },
    "3333": {
      "행정구역": "충청북도 옥천군",
      "기관_명": "옥천군"
    },
    "3334": {
      "행정구역": "충청북도 영동군",
      "기관_명": "영동군"
    },
    "3335": {
      "행정구역": "충청북도 진천군",
      "기관_명": "진천군"
    },
    "3336": {
      "행정구역": "충청북도 괴산군",
      "기관_명": "괴산군"
    },
    "3337": {
      "행정구역": "충청북도 음성군",
      "기관_명": "음성군"
    },
    "3340": {
      "행정구역": "충청북도 단양군",
      "기관_명": "단양군"
    },
    "3341": {
      "행정구역": "충청북도 증평군",
      "기관_명": "증평군"
    },
    "3400": {
      "행정구역": "충청남도",
      "기관_명": "충청남도"
    },
    "3412": {
      "행정구역": "충청남도 공주시",
      "기관_명": "공주시"
    },
    "3415": {
      "행정구역": "충청남도 서산시",
      "기관_명": "서산시"
    },
    "3416": {
      "행정구역": "충청남도 보령시",
      "기관_명": "보령시"
    },
    "3417": {
      "행정구역": "충청남도 아산시",
      "기관_명": "아산시"
    },
    "3418": {
      "행정구역": "충청남도 논산시",
      "기관_명": "논산시"
    },
    "3419": {
      "행정구역": "충청남도 계룡시",
      "기관_명": "계룡시"
    },
    "3420": {
      "행정구역": "충청남도 천안시 동남구",
      "기관_명": "천안시동남구"
    },
    "3421": {
      "행정구역": "충청남도 천안시 서북구",
      "기관_명": "천안시서북구"
    },
    "3422": {
      "행정구역": "충청남도 당진시",
      "기관_명": "당진시"
    },
    "3431": {
      "행정구역": "충청남도 금산군",
      "기관_명": "금산군"
    },
    "3436": {
      "행정구역": "충청남도 부여군",
      "기관_명": "부여군"
    },
    "3437": {
      "행정구역": "충청남도 서천군",
      "기관_명": "서천군"
    },
    "3439": {
      "행정구역": "충청남도 청양군",
      "기관_명": "청양군"
    },
    "3440": {
      "행정구역": "충청남도 홍성군",
      "기관_명": "홍성군"
    },
    "3441": {
      "행정구역": "충청남도 예산군",
      "기관_명": "예산군"
    },
    "3446": {
      "행정구역": "충청남도 태안군",
      "기관_명": "태안군"
    },
    "3500": {
      "행정구역": "전라북도",
      "기관_명": "전라북도"
    },
    "3501": {
      "행정구역": "전라북도 전주시 완산구",
      "기관_명": "전주시완산구"
    },
    "3502": {
      "행정구역": "전라북도 전주시 덕진구",
      "기관_명": "전주시덕진구"
    },
    "3512": {
      "행정구역": "전라북도 군산시",
      "기관_명": "군산시"
    },
    "3515": {
      "행정구역": "전라북도 남원시",
      "기관_명": "남원시"
    },
    "3516": {
      "행정구역": "전라북도 김제시",
      "기관_명": "김제시"
    },
    "3517": {
      "행정구역": "전라북도 정읍시",
      "기관_명": "정읍시"
    },
    "3518": {
      "행정구역": "전라북도 익산시",
      "기관_명": "익산시"
    },
    "3531": {
      "행정구역": "전라북도 완주군",
      "기관_명": "완주군"
    },
    "3532": {
      "행정구역": "전라북도 진안군",
      "기관_명": "진안군"
    },
    "3533": {
      "행정구역": "전라북도 무주군",
      "기관_명": "무주군"
    },
    "3534": {
      "행정구역": "전라북도 장수군",
      "기관_명": "장수군"
    },
    "3535": {
      "행정구역": "전라북도 임실군",
      "기관_명": "임실군"
    },
    "3537": {
      "행정구역": "전라북도 순창군",
      "기관_명": "순창군"
    },
    "3539": {
      "행정구역": "전라북도 고창군",
      "기관_명": "고창군"
    },
    "3540": {
      "행정구역": "전라북도 부안군",
      "기관_명": "부안군"
    },
    "3600": {
      "행정구역": "전라남도",
      "기관_명": "전라남도"
    },
    "3611": {
      "행정구역": "전라남도 목포시",
      "기관_명": "목포시"
    },
    "3612": {
      "행정구역": "전라남도 여수시",
      "기관_명": "중부민원출장소"
    },
    "3613": {
      "행정구역": "전라남도 순천시",
      "기관_명": "순천시"
    },
    "3614": {
      "행정구역": "전라남도 나주시",
      "기관_명": "나주시"
    },
    "3618": {
      "행정구역": "전라남도 광양시",
      "기관_명": "광양시"
    },
    "3632": {
      "행정구역": "전라남도 담양군",
      "기관_명": "담양군"
    },
    "3633": {
      "행정구역": "전라남도 곡성군",
      "기관_명": "곡성군"
    },
    "3634": {
      "행정구역": "전라남도 구례군",
      "기관_명": "구례군"
    },
    "3638": {
      "행정구역": "전라남도 고흥군",
      "기관_명": "고흥군"
    },
    "3639": {
      "행정구역": "전라남도 보성군",
      "기관_명": "보성군"
    },
    "3640": {
      "행정구역": "전라남도 화순군",
      "기관_명": "화순군"
    },
    "3641": {
      "행정구역": "전라남도 장흥군",
      "기관_명": "장흥군"
    },
    "3642": {
      "행정구역": "전라남도 강진군",
      "기관_명": "강진군"
    },
    "3643": {
      "행정구역": "전라남도 해남군",
      "기관_명": "해남군"
    },
    "3644": {
      "행정구역": "전라남도 영암군",
      "기관_명": "영암군"
    },
    "3645": {
      "행정구역": "전라남도 무안군",
      "기관_명": "무안군"
    },
    "3647": {
      "행정구역": "전라남도 함평군",
      "기관_명": "함평군"
    },
    "3648": {
      "행정구역": "전라남도 영광군",
      "기관_명": "영광군"
    },
    "3649": {
      "행정구역": "전라남도 장성군",
      "기관_명": "장성군"
    },
    "3650": {
      "행정구역": "전라남도 완도군",
      "기관_명": "완도군"
    },
    "3651": {
      "행정구역": "전라남도 진도군",
      "기관_명": "진도군"
    },
    "3652": {
      "행정구역": "전라남도 신안군",
      "기관_명": "신안군"
    },
    "3700": {
      "행정구역": "경상북도",
      "기관_명": "경상북도"
    },
    "3712": {
      "행정구역": "경상북도 경주시",
      "기관_명": "경주시"
    },
    "3713": {
      "행정구역": "경상북도 김천시",
      "기관_명": "김천시"
    },
    "3714": {
      "행정구역": "경상북도 안동시",
      "기관_명": "안동시"
    },
    "3715": {
      "행정구역": "경상북도 구미시",
      "기관_명": "선산출장소"
    },
    "3716": {
      "행정구역": "경상북도 영주시",
      "기관_명": "영주시"
    },
    "3717": {
      "행정구역": "경상북도 영천시",
      "기관_명": "영천시"
    },
    "3718": {
      "행정구역": "경상북도 상주시",
      "기관_명": "상주시"
    },
    "3720": {
      "행정구역": "경상북도 경산시",
      "기관_명": "경산시"
    },
    "3721": {
      "행정구역": "경상북도 포항시 남구",
      "기관_명": "포항시 남구"
    },
    "3722": {
      "행정구역": "경상북도 포항시 북구",
      "기관_명": "포항시 북구"
    },
    "3723": {
      "행정구역": "경상북도 문경시",
      "기관_명": "문경시"
    },
    "3733": {
      "행정구역": "경상북도 의성군",
      "기관_명": "의성군"
    },
    "3735": {
      "행정구역": "경상북도 청송군",
      "기관_명": "청송군"
    },
    "3736": {
      "행정구역": "경상북도 영양군",
      "기관_명": "영양군"
    },
    "3737": {
      "행정구역": "경상북도 영덕군",
      "기관_명": "영덕군"
    },
    "3742": {
      "행정구역": "경상북도 청도군",
      "기관_명": "청도군"
    },
    "3743": {
      "행정구역": "경상북도 고령군",
      "기관_명": "고령군"
    },
    "3744": {
      "행정구역": "경상북도 성주군",
      "기관_명": "성주군"
    },
    "3745": {
      "행정구역": "경상북도 칠곡군",
      "기관_명": "칠곡군"
    },
    "3750": {
      "행정구역": "경상북도 예천군",
      "기관_명": "예천군"
    },
    "3752": {
      "행정구역": "경상북도 봉화군",
      "기관_명": "봉화군"
    },
    "3753": {
      "행정구역": "경상북도 울진군",
      "기관_명": "울진군"
    },
    "3754": {
      "행정구역": "경상북도 울릉군",
      "기관_명": "울릉군"
    },
    "3800": {
      "행정구역": "경상남도",
      "기관_명": "경상남도"
    },
    "3806": {
      "행정구역": "경상남도 창원시 의창구",
      "기관_명": "창원시 의창구"
    },
    "3807": {
      "행정구역": "경상남도 창원시 성산구",
      "기관_명": "창원시 성산구"
    },
    "3808": {
      "행정구역": "경상남도 창원시 마산합포구",
      "기관_명": "창원시 마산합포구"
    },
    "3809": {
      "행정구역": "경상남도 창원시 마산회원구",
      "기관_명": "창원시 마산회원구"
    },
    "3810": {
      "행정구역": "경상남도 창원시 진해구",
      "기관_명": "창원시 진해구"
    },
    "3813": {
      "행정구역": "경상남도 진주시",
      "기관_명": "진주시"
    },
    "3818": {
      "행정구역": "경상남도 김해시",
      "기관_명": "장유출장소"
    },
    "3819": {
      "행정구역": "경상남도 밀양시",
      "기관_명": "밀양시"
    },
    "3822": {
      "행정구역": "경상남도 통영시",
      "기관_명": "통영시"
    },
    "3823": {
      "행정구역": "경상남도 거제시",
      "기관_명": "거제시"
    },
    "3824": {
      "행정구역": "경상남도 사천시",
      "기관_명": "사천시"
    },
    "3825": {
      "행정구역": "경상남도 양산시",
      "기관_명": "웅상민원출장소"
    },
    "3832": {
      "행정구역": "경상남도 의령군",
      "기관_명": "의령군"
    },
    "3833": {
      "행정구역": "경상남도 함안군",
      "기관_명": "함안군"
    },
    "3834": {
      "행정구역": "경상남도 창녕군",
      "기관_명": "창녕군"
    },
    "3842": {
      "행정구역": "경상남도 고성군",
      "기관_명": "고성군"
    },
    "3844": {
      "행정구역": "경상남도 남해군",
      "기관_명": "남해군"
    },
    "3845": {
      "행정구역": "경상남도 하동군",
      "기관_명": "하동군"
    },
    "3846": {
      "행정구역": "경상남도 산청군",
      "기관_명": "산청군"
    },
    "3847": {
      "행정구역": "경상남도 함양군",
      "기관_명": "함양군"
    },
    "3848": {
      "행정구역": "경상남도 거창군",
      "기관_명": "거창군"
    },
    "3849": {
      "행정구역": "경상남도 합천군",
      "기관_명": "합천군"
    },
    "9100": {
      "행정구역": "제주특별자치도",
      "기관_명": "제주특별자치도"
    },
    "9111": {
      "행정구역": "제주특별자치도 제주시",
      "기관_명": "제주시"
    },
    "9112": {
      "행정구역": "제주특별자치도 서귀포시",
      "기관_명": "서귀포시"
    }
  }
}
